my_yhk/__init__.py
my_yhk/convert2py.py
my_yhk-0.1.0.dist-info/METADATA
my_yhk-0.1.0.dist-info/WHEEL
my_yhk-0.1.0.dist-info/RECORD
