Metadata-Version: 2.3
Name: my-yhk
Version: 0.1.0
Summary: 
Author: yanghknlp
Author-email: yanghknlp@gmail.com
Requires-Python: >=3.9, <4
Classifier: Programming Language :: Python :: 3
Classifier: Programming Language :: Python :: 3.9
Classifier: Programming Language :: Python :: 3.10
Classifier: Programming Language :: Python :: 3.11
Classifier: Programming Language :: Python :: 3.12
Classifier: Programming Language :: Python :: 3.13
Requires-Dist: jiaba (>=0.0.1,<0.0.2)
Requires-Dist: jieba (>=0.42.1,<0.43.0)
Requires-Dist: pypinyin (>=0.55.0,<0.56.0)
